Workbook

Sheet Calculator
A1: GlowNest Amazon Campaign Profitability Calculator
A3: INPUT SECTION (Editable)
A4: Selling Price (SP) | B4: 800 | C4: Customer retail listing price on Amazon India
A5: Cost of Goods Sold (COGS) | B5: 280 | C5: Manufacturing + shipping to Amazon warehouse
A6: Amazon Referral Fee (%) | B6: 0.12 | C6: Category commission fee charged by Amazon
A7: Monthly Ad Spend | B7: 300000 | C7: Total advertising budget allocated for the month
A8: Units Sold via Ads | B8: 1500 | C8: Total volume of sales attributed directly to ads
A9: Organic Units Sold | B9: 2000 | C9: Total volume of sales generated from search engine rankings
A10: Fixed Costs (monthly) | B10: 150000 | C10: Warehousing, team payroll, software subscriptions
A12: OUTPUT SECTION (Auto-Calculated)
A13: Gross Margin per Unit | B13: =B4-B5 | C13: =SP - COGS
A14: Amazon Fee per Unit | B14: =B4*B6 | C14: =SP * Fee %
A15: Ad Cost per Unit | B15: =B7/B8 | C15: =Ad Spend / Ad Units
A16: Net Margin (Ad Units) | B16: =B13-B14-B15 | C16: =Gross Margin - Amazon Fee - Ad Cost per Unit
A17: Net Margin (Organic Units) | B17: =B13-B14 | C17: =Gross Margin - Amazon Fee
A18: Total Monthly Revenue | B18: =B4*(B8+B9) | C18: =SP * (Ad Units + Organic Units)
A19: Total Monthly Profit | B19: =(B16*B8)+(B17*B9)-B10 | C19: =(Net Margin Ad * Ad Units) + (Net Margin Org * Org Units) - Fixed Costs
A20: ACOS | B20: =B7/(B4*B8) | C20: =Ad Spend / Ad Revenue
A21: TACOS | B21: =B7/B18 | C21: =Ad Spend / Total Revenue
A22: Break-Even Ad Spend | B22: =B17*(B8+B9)-B10 | C22: Total contribution margin minus fixed costs

Sheet Scenario Explorer
A1: Scenario Analysis (Answers to Model Exploration)
A3: Metric | B3: Base Case | C3: Price Sensitivity | D3: Cost Pressure | E3: Organic Growth | F3: Category Shift
A4: Selling Price (SP) | B4: 800 | C4: 950 | D4: 800 | E4: 800 | F4: 700
A5: COGS | B5: 280 | C5: 280 | D5: 336 | E5: 280 | F5: 280
A6: Amazon Referral Fee (%) | B6: 0.12 | C6: 0.12 | D6: 0.12 | E6: 0.12 | F6: 0.12
A7: Monthly Ad Spend | B7: 300000 | C7: 300000 | D7: 300000 | E7: 300000 | F7: 300000
A8: Units Sold via Ads | B8: 1500 | C8: 1500 | D8: 1500 | E8: 1500 | F8: 1500
A9: Organic Units Sold | B9: 2000 | C9: 2000 | D9: 2000 | E9: 3500 | F9: 2000
A10: Fixed Costs (monthly) | B10: 150000 | C10: 150000 | D10: 150000 | E10: 150000 | F10: 150000
A11: Calculated Outputs
A12: Gross Margin per Unit | B12: =B4-B5 | C12: =C4-C5 | D12: =D4-D5 | E12: =E4-E5 | F12: =F4-F5
A13: Amazon Fee per Unit | B13: =B4*B6 | C13: =C4*C6 | D13: =D4*D6 | E13: =E4*E6 | F13: =F4*F6
A14: Ad Cost per Unit | B14: =B7/B8 | C14: =C7/C8 | D14: =D7/D8 | E14: =E7/E8 | F14: =F7/F8
A15: Net Margin (Ad Units) | B15: =B12-B13-B14 | C15: =C12-C13-C14 | D15: =D12-D13-D14 | E15: =E12-E13-E14 | F15: =F12-F13-F14
A16: Net Margin (Organic Units) | B16: =B12-B13 | C16: =C12-C13 | D16: =D12-D13 | E16: =E12-E13 | F16: =F12-F13
A17: Total Monthly Revenue | B17: =B4*(B8+B9) | C17: =C4*(C8+C9) | D17: =D4*(D8+D9) | E17: =E4*(E8+E9) | F17: =F4*(F8+F9)
A18: Total Monthly Profit | B18: =(B15*B8)+(B16*B9)-B10 | C18: =(C15*C8)+(C16*C9)-C10 | D18: =(D15*D8)+(D16*D9)-D10 | E18: =(E15*E8)+(E16*E9)-E10 | F18: =(F15*F8)+(F16*F9)-F10
A19: ACOS | B19: =B7/(B4*B8) | C19: =C7/(C4*C8) | D19: =D7/(D4*D8) | E19: =E7/(E4*E8) | F19: =F7/(F4*F8)
A20: TACOS | B20: =B7/B17 | C20: =C7/C17 | D20: =D7/D17 | E20: =E7/E17 | F20: =F7/F17
A21: Break-Even Ad Spend | B21: =B16*(B8+B9)-B10 | C21: =C16*(C8+C9)-C10 | D21: =D16*(D8+D9)-D10 | E21: =E16*(E8+E9)-E10 | F21: =F16*(F8+F9)-F10

Sheet Chart Data & Viz
A1: Ad Spend vs. Net Profit Analysis
A3: Monthly Ad Spend | B3: Total Monthly Profit | C3: TACOS
A4: 0 | B4: =Calculator!$B$17*(0+Calculator!$B$9)-A4-Calculator!$B$10 | C4: =A4/(Calculator!$B$4*(0+Calculator!$B$9))
A5: 50000 | B5: =Calculator!$B$17*(480+Calculator!$B$9)-A5-Calculator!$B$10 | C5: =A5/(Calculator!$B$4*(480+Calculator!$B$9))
A6: 100000 | B6: =Calculator!$B$17*(850+Calculator!$B$9)-A6-Calculator!$B$10 | C6: =A6/(Calculator!$B$4*(850+Calculator!$B$9))
A7: 150000 | B7: =Calculator!$B$17*(1100+Calculator!$B$9)-A7-Calculator!$B$10 | C7: =A7/(Calculator!$B$4*(1100+Calculator!$B$9))
A8: 200000 | B8: =Calculator!$B$17*(1280+Calculator!$B$9)-A8-Calculator!$B$10 | C8: =A8/(Calculator!$B$4*(1280+Calculator!$B$9))
A9: 250000 | B9: =Calculator!$B$17*(1400+Calculator!$B$9)-A9-Calculator!$B$10 | C9: =A9/(Calculator!$B$4*(1400+Calculator!$B$9))
A10: 300000 | B10: =Calculator!$B$17*(1500+Calculator!$B$9)-A10-Calculator!$B$10 | C10: =A10/(Calculator!$B$4*(1500+Calculator!$B$9))
A11: 400000 | B11: =Calculator!$B$17*(1680+Calculator!$B$9)-A11-Calculator!$B$10 | C11: =A11/(Calculator!$B$4*(1680+Calculator!$B$9))
A12: 500000 | B12: =Calculator!$B$17*(2100+Calculator!$B$9)-A12-Calculator!$B$10 | C12: =A12/(Calculator!$B$4*(2100+Calculator!$B$9))
A13: 600000 | B13: =Calculator!$B$17*(2500+Calculator!$B$9)-A13-Calculator!$B$10 | C13: =A13/(Calculator!$B$4*(2500+Calculator!$B$9))
A14: 750000 | B14: =Calculator!$B$17*(2750+Calculator!$B$9)-A14-Calculator!$B$10 | C14: =A14/(Calculator!$B$4*(2750+Calculator!$B$9))
A15: 900000 | B15: =Calculator!$B$17*(2900+Calculator!$B$9)-A15-Calculator!$B$10 | C15: =A15/(Calculator!$B$4*(2900+Calculator!$B$9))
A16: 1200000 | B16: =Calculator!$B$17*(3100+Calculator!$B$9)-A16-Calculator!$B$10 | C16: =A16/(Calculator!$B$4*(3100+Calculator!$B$9))
